edempy_wrapper/DataExtractor.py
edempy_wrapper/ExperimentBase.py
edempy_wrapper/LoadExperimentData.py
edempy_wrapper/__init__.py
edempy_wrapper/extract_contacts_v2.py
edempy_wrapper/main.py
edempy_wrapper/read_experiment.py
edempy_wrapper/visualisation.py
edempy_wrapper-0.1.1.dist-info/METADATA
edempy_wrapper-0.1.1.dist-info/WHEEL
edempy_wrapper-0.1.1.dist-info/top_level.txt
edempy_wrapper-0.1.1.dist-info/RECORD
