Metadata-Version: 2.1
Name: edempy_wrapper
Version: 0.1.1
Summary: A package for analyzing EDEM simulation data
Author: Deniz Canbay
Author-email: decanbay@gmail.com
Classifier: Programming Language :: Python :: 3
Classifier: License :: OSI Approved :: MIT License
Classifier: Operating System :: OS Independent
Requires-Python: >=3.8,<3.9
Requires-Dist: numpy
Requires-Dist: matplotlib
Requires-Dist: pandas
Requires-Dist: tqdm
Requires-Dist: pyvista
Requires-Dist: imageio
